{
  "project_info": {
    "project_number": "975370739037",
    "project_id": "health-chatbot-fc1cb",
    "storage_bucket": "health-chatbot-fc1cb.firebasestorage.app"
  },
  "client": [
    {
      "client_info": {
        "mobilesdk_app_id": "1:975370739037:android:2b9541cd4db4410c60dcb4",
        "android_client_info": {
          "package_name": "com.example.myapplication"
        }
      },
      "oauth_client": [],
      "api_key": [
        {
          "current_key": "AIzaSyCoWwoSbuMyEE2KqbzuW1PplAYe_vV6lPw"
        }
      ],
      "services": {
        "appinvite_service": {
          "other_platform_oauth_client": []
        }
      }
    },
    {
      "client_info": {
        "mobilesdk_app_id": "1:975370739037:android:795b4dad01c0725160dcb4",
        "android_client_info": {
          "package_name": "com.example.unit1"
        }
      },
      "oauth_client": [],
      "api_key": [
        {
          "current_key": "AIzaSyCoWwoSbuMyEE2KqbzuW1PplAYe_vV6lPw"
        }
      ],
      "services": {
        "appinvite_service": {
          "other_platform_oauth_client": []
        }
      }
    }
  ],
  "configuration_version": "1"
}